plbmng/__init__.py
plbmng/engine.py
plbmng/nor.txt
plbmng/conf/__init__.py
plbmng/conf/plbmng.conf
plbmng/database/default.node
plbmng/database/first.boolean
plbmng/database/internal.db
plbmng/database/planetlab_21-03-17_14-32.node
plbmng/lib/__init__.py
plbmng/lib/full_map.py
plbmng/lib/icmp_map.py
plbmng/lib/map_one.py
plbmng/lib/planetlab_list_creator.py
plbmng/lib/port_scanner.py
plbmng/lib/ssh_map.py
plbmng/lib/__pycache__/__init__.cpython-37.pyc
plbmng/lib/__pycache__/planetlab_list_creator.cpython-37.pyc
plbmng/logs/__init__.py
plbmng-0.3.7.data/scripts/plbmng
plbmng-0.3.7.dist-info/LICENSE
plbmng-0.3.7.dist-info/METADATA
plbmng-0.3.7.dist-info/WHEEL
plbmng-0.3.7.dist-info/dependency_links.txt
plbmng-0.3.7.dist-info/top_level.txt
plbmng-0.3.7.dist-info/RECORD
