Metadata-Version: 2.1
Name: plbmng
Version: 0.3.7
Summary: Tool for monitoring PlanetLab network
Home-page: https://github.com/Andrasov/PlanetLab.git
Author: Ivan Andrasov
Author-email: xandra03@stud.feec.vutbr.cz
License: MIT
Platform: UNKNOWN
Requires-Dist: vincent
Requires-Dist: folium
Requires-Dist: numpy
Requires-Dist: pandas
Requires-Dist: geocoder
Requires-Dist: paramiko
Requires-Dist: pythondialog
